{"amiable": 0, "beauty": 1, "charles": 2, "dull": 3, "estate": 4, "heir": 5, "large": 6, "rather": 7, "-pron-": 8, "around": 9, "funny": 10, "like": 11, "real": 12, "somebody": 13, "witty": 14, "always": 15, "ian": 16, "important": 17, "keep": 18, "lid": 19, "manage": 20, "part": 21, "wright": 22, "belfast": 23, "even": 24, "everywhere": 25, "filming": 26, "gun": 27, "joyous": 28, "people": 29, "really": 30, "though": 31, "blossom": 32, "energetic": 33, "exuberant": 34, "play": 35, "smurf": 36, "arab": 37, "bower": 38, "lovable": 39, "present": 40, "uncle": 41, "warm": 42, "another": 43, "back": 44, "celebrate": 45, "come": 46, "hard": 47, "image": 48, "pop": 49, "ready": 50, "success": 51, "team": 52, "word": 53, "work": 54, "yet": 55, "cook": 56, "everything": 57, "pan": 58, "drink": 59, "kathie": 60, "lee": 61, "name": 62, "refreshing": 63, "almost": 64, "catch": 65, "celebration": 66, "everyone": 67, "glass": 68, "hold": 69, "shoot": 70, "taste": 71, "wine": 72, "--": 73, "conversation": 74, "jenkins": 75, "know": 76, "old": 77, "self": 78, "sueann": 79, "tell": 80, "cavuto": 81, "get": 82, "little": 83, "market": 84, "naysayer": 85, "rich": 86, "say": 87, "earn": 88, "extrovert": 89, "eye": 90, "jackie": 91, "nickname": 92, "slant": 93, "vaguely": 94, "egg": 95, "epitomize": 96, "feel": 97, "fish": 98, "leach": 99, "phrase": 100, "robin": 101, "tiny": 102, "trademark": 103, "'d": 104, "david": 105, "meet": 106, "smith": 107, "susan": 108, "think": 109, "go": 110, "holton": 111, "ilish": 112, "join": 113, "katie": 114, "leom": 115, "quieter": 116, "seem": 117, "two": 118, "begin": 119, "bright": 120, "fade": 121, "hope": 122, "light": 123, "mckeown": 124, "soon": 125, "would": 126, "last": 127, "least": 128, "love": 129, "well": 130, "whoop": 131, "american": 132, "full": 133, "life": 134, "vivacious": 135, "colorfast": 136, "colour": 137, "copper": 138, "factor": 139, "look": 140, "max": 141, "passion": 142, "peach": 143, "sparkle": 144, "spirits": 145, "alloy": 146, "due": 147, "flow": 148, "mean": 149, "metal": 150, "often": 151, "possibly": 152, "rough": 153, "see": 154, "shortage": 155, "surface": 156, "tin": 157, "also": 158, "mills": 159, "resilient": 160, "samaritan": 161, "'s": 162, "blanc": 163, "bullate": 164, "far": 165, "furthermore": 166, "leaf": 167, "less": 168, "pinot": 169, "vein": 170, "time": 171, "edge": 172, "great": 173, "lady": 174, "voice": 175, "among": 176, "bite": 177, "bug": 178, "chubby": 179, "fats": 180, "first": 181, "jazzman": 182, "london": 183, "waller": 184, "guest": 185, "let": 186, "lunch": 187, "one": 188, "big": 189, "blonde": 190, "family": 191, "hollywood": 192, "yearn": 193, "bashful": 194, "brash": 195, "dandy": 196, "darlington": 197, "loud": 198, "normally": 199, "award": 200, "battle": 201, "dance": 202, "en": 203, "female": 204, "good": 205, "madonna": 206, "prepare": 207, "star": 208, "superstar": 209, "video": 210, "vogue": 211, "45": 212, "board": 213, "host": 214, "hotel": 215, "julie": 216, "offer": 217, "service": 218, "smile": 219, "super": 220, "title": 221, "tourist": 222, "wales": 223, "welcome": 224, "certainly": 225, "character": 226, "everton": 227, "fan": 228, "favourite": 229, "mate": 230, "may": 231, "2.5": 232, "addiction": 233, "admit": 234, "boyish": 235, "child": 236, "front": 237, "live": 238, "million": 239, "presenter": 240, "television": 241, "viewer": 242, "breast": 243, "cancer": 244, "form": 245, "future": 246, "medication": 247, "operation": 248, "plan": 249, "still": 250, "take": 251, "top": 252, "cinderella": 253, "claire": 254, "enough": 255, "force": 256, "former": 257, "foster": 258, "lifestyle": 259, "mother": 260, "natural": 261, "parent": 262, "schoolgirl": 263, "want": 264, "clothe": 265, "cottage": 266, "eileen": 267, "floor": 268, "girl": 269, "help": 270, "make": 271, "office": 272, "remember": 273, "scrub": 274, "selina": 275, "small": 276, "dividend": 277, "result": 278, "romp": 279, "shareholder": 280, "south": 281, "water": 282, "welsh": 283, "west": 284, "drop": 285, "fringe": 286, "grow": 287, "lock": 288, "never": 289, "square": 290, "unless": 291, "beam": 292, "else": 293, "flirtatiously": 294, "ignore": 295, "marcel": 296, "protest": 297, "someone": 298, "continue": 299, "couple": 300, "diet": 301, "emerge": 302, "kim": 303, "load": 304, "reduce": 305, "shed": 306, "stone": 307, "weight": 308, "aerate": 309, "champagne": 310, "finish": 311, "shower": 312, "specially": 313, "sprinkle": 314, "toe": 315, "touch": 316, "ultimate": 317, "unit": 318, "angry": 319, "finger": 320, "localized": 321, "quite": 322, "spread": 323, "area": 324, "30": 325, "bake": 326, "crisp": 327, "minute": 328, "ensure": 329, "popular": 330, "year": 331, "alicia": 332, "aunt": 333, "find": 334, "nephew": 335, "sara": 336, "solace": 337, "zestful": 338, "fun": 339, "much": 340, "show": 341, "try": 342, "class": 343, "fourth": 344, "noisy": 345, "500e": 346, "brenda": 347, "gs": 348, "motorcycle": 349, "owner": 350, "pass": 351, "proud": 352, "recently": 353, "speedy": 354, "suzuki": 355, "test": 356, "alison": 357, "changed": 358, "friend": 359, "man": 360, "carefully": 361, "dress": 362, "excited": 363, "excitement": 364, "express": 365, "hang": 366, "laughter": 367, "singing": 368, "sort": 369, "tomorrow": 370, "wardrobe": 371, "blow": 372, "referee": 373, "whistle": 374, "bottle": 375, "equipment": 376, "money": 377, "production": 378, "spend": 379, "win": 380, "clare": 381, "4th": 382, "7": 383, "august": 384, "p.m": 385, "petite": 386, "student": 387, "sunday": 388, "add": 389, "atmosphere": 390, "extended": 391, "occasion": 392, "range": 393, "black": 394, "blister": 395, "skin": 396, "lively": 397, "new": 398, "sadly": 399, "short": 400, "successful": 401, "supply": 402, "zealand": 403, "deuce": 404, "slender": 405, "contrast": 406, "diana": 407, "giggly": 408, "vacuous": 409, "way": 410, "achieve": 411, "busy": 412, "day": 413, "liz": 414, "quicker": 415, "style": 416, "today": 417, "towards": 418, "trend": 419, "tune": 420, "wave": 421, "appear": 422, "cow": 423, "hoof": 424, "johnny": 425, "lowing": 426, "mister": 427, "pull": 428, "slowly": 429, "soft": 430, "talk": 431, "arrange": 432, "delivery": 433, "fondly": 434, "happy": 435, "hour": 436, "imagine": 437, "instantly": 438, "magick": 439, "sad": 440, "something": 441, "taxi": 442, "within": 443, "wordsley": 444, "82": 445, "describe": 446, "granddaughter": 447, "josephine": 448, "vigour": 449, "wife": 450, "wonderful": 451, "actress": 452, "ever": 453, "funniest": 454, "must": 455, "need": 456, "speech": 457, "write": 458, "condition": 459, "nature": 460, "outgoing": 461, "philippa": 462, "band": 463, "devitrify": 464, "frothy": 465, "glassy": 466, "interleave": 467, "lavas": 468, "layer": 469, "material": 470, "unaltered": 471, "baby": 472, "blue": 473, "joan": 474, "match": 475, "pyman": 476, "wear": 477, "evening": 478, "fancy": 479, "maybe": 480, "stardom": 481, "right": 482, "yes": 483, "blandford": 484, "free": 485, "jail": 486, "judge": 487, "liberty": 488, "marquess": 489, "mistake": 490, "toast": 491, "answer": 492, "phone": 493, "confident": 494, "call": 495, "fashion": 496, "france": 497, "house": 498, "industry": 499, "laurent": 500, "perfume": 501, "saint": 502, "throat": 503, "unveil": 504, "yves": 505, "act": 506, "boy": 507, "n't": 508, "jocks": 509, "scotland": 510, "jock": 511, "c": 512, "j": 513, "k": 514, "creature": 515, "thirteen": 516, "complex": 517, "device": 518, "driver": 519, "handle": 520, "interfac": 521, "operating": 522, "system": 523, "aspect": 524, "bit": 525, "buy": 526, "certain": 527, "explain": 528, "marks": 529, "mrs": 530, "shrink": 531, "spencer": 532, "thatcher": 533, "underwear": 534, "addition": 535, "ergoclient": 536, "ergoview": 537, "module": 538, "relevant": 539, "terminal": 540, "upgrade": 541, "action": 542, "although": 543, "bear": 544, "biology": 545, "choice": 546, "circumscribe": 547, "context": 548, "cultural": 549, "element": 550, "feature": 551, "social": 552, "virtue": 553, "acclaim": 554, "charismatic": 555, "count": 556, "defeater": 557, "elect": 558, "emperor": 559, "empire": 560, "generalship": 561, "mandred": 562, "period": 563, "recovery": 564, "respected": 565, "skaven": 566, "together": 567, "vulnerable": 568, "contemporary": 569, "franz": 570, "include": 571, "karl": 572, "selection": 573, "army": 574, "choose": 575, "famous": 576, "list": 577, "put": 578, "represent": 579, "virtually": 580, "careful": 581, "enter": 582, "procedure": 583, "profession": 584, "training": 585, "competence": 586, "deficiency": 587, "deficit": 588, "effect": 589, "gap": 590, "learning": 591, "matching": 592, "model": 593, "poor": 594, "propose": 595, "quality": 596, "task": 597, "teaching": 598, "weak": 599, "central": 600, "change": 601, "level": 602, "skill": 603, "strategy": 604, "teacher": 605, "tyes": 606, "approach": 607, "expertise": 608, "follow": 609, "importance": 610, "point": 611, "sociological": 612, "study": 613, "transmission": 614, "business": 615, "customer": 616, "depend": 617, "relationship": 618, "requirement": 619, "credit": 620, "give": 621, "suspect": 622, "ask": 623, "could": 624, "doctor": 625, "opinion": 626, "psychiatric": 627, "x": 628, "bad": 629, "become": 630, "established": 631, "habit": 632, "friendly": 633, "martin": 634, "notably": 635, "receptionist": 636, "sheila": 637, "anything": 638, "barman": 639, "colourless": 640, "corrigan": 641, "devoted": 642, "follower": 643, "race": 644, "somewhat": 645, "strong": 646, "tim": 647, "view": 648, "easy": 649, "hyperactive": 650, "parody": 651, "subject": 652, "america": 653, "capture": 654, "eager": 655, "egoistic": 656, "emergent": 657, "forthright": 658, "place": 659, "rap": 660, "scene": 661, "uk": 662, "young": 663, "problem": 664, "recall": 665, "bin": 666, "bomber": 667, "circus": 668, "cult": 669, "laden": 670, "suicide": 671, "bloom": 672, "understand": 673, "americans": 674, "especially": 675, "gibson": 676, "likable": 677, "lot": 678, "different": 679, "qwq": 680, "stahl": 681, "genetic": 682, "predisposition": 683, "simply": 684, "speak": 685, "upbeat": 686, "beach": 687, "kind": 688, "split": 689, "humorous": 690, "rule": 691, "throw": 692, "1973": 693, "comparable": 694, "fact": 695, "field": 696, "measure": 697, "nixon": 698, "poll": 699, "resignation": 700, "richard": 701, "term": 702, "divorce": 703, "ooh": 704, "kotb": 705, "radio": 706, "wendy": 707, "williams": 708, "york": 709, "horse": 710, "music": 711, "connect": 712, "role": 713, "behind": 714, "situation": 715, "dominate": 716, "magnetism": 717, "ted": 718, "believe": 719, "celebrity": 720, "election": 721, "roll": 722, "sell": 723, "dollar": 724, "million-": 725, "anguish": 726, "cover": 727, "attractive": 728, "afraid": 729, "council": 730, "davis": 731, "democrat": 732, "fellow": 733, "country": 734, "berlioz": 735, "bigness": 736, "colin": 737, "musical": 738, "side": 739, "engaging": 740, "draw": 741, "notorious": 742, "particular": 743, "performer": 744, "focus": 745, "thus": 746, "bush": 747, "energy": 748, "personally": 749, "president": 750, "abstract": 751, "book": 752, "concept": 753, "desire": 754, "destiny": 755, "dream": 756, "dysfunctional": 757, "eponymous": 758, "revolve": 759, "sandman": 760, "accomplishment": 761, "amount": 762, "astonishing": 763, "fill": 764, "story": 765, "tremendous": 766, "vivid": 767, "appearance": 768, "human": 769, "ordinarily": 770, "submerge": 771, "uniform": 772, "vary": 773, "convey": 774, "affect": 775, "anywhere": 776, "husband": 777, "issue": 778, "noor": 779, "policy": 780, "queen": 781, "region": 782, "whether": 783, "account": 784, "clearly": 785, "political": 786, "4": 787, "bevilacqua": 788, "behavior": 789, "culture": 790, "dialogue": 791, "lack": 792, "fascinate": 793, "particularly": 794, "plot": 795, "rivalry": 796, "stabbing": 797, "artistry": 798, "challenge": 799, "marketing": 800, "marry": 801, "movie": 802, "savvy": 803, "city": 804, "landscape": 805, "reflection": 806, "root": 807, "wildlife": 808, "odd": 809, "reveal": 810, "secret": 811, "sleep": 812, "asleep": 813, "fall": 814, "paper": 815, "pen": 816, "position": 817, "tonight": 818, "dr": 819, "six": 820, "generate": 821, "heat": 822, "mannerism": 823, "bring": 824, "interesting": 825, "psychopathic": 826, "-lrb-": 827, "-rrb-": 828, "1980s": 829, "break": 830, "chung": 831, "clash": 832, "clip": 833, "end": 834, "``": 835, "bob": 836, "candidate": 837, "democratic": 838, "graham": 839, "oversupply": 840, "presidential": 841, "senator": 842, "vehemence": 843, "lead": 844, "stature": 845, "edwards": 846, "gephardt": 847, "identify": 848, "kerry": 849, "labor": 850, "rookie": 851, "insight": 852, "ph": 853, "sense": 854, "taunt": 855, "type": 856, "hear": 857, "month": 858, "number": 859, "probably": 860, "distinct": 861, "king": 862, "larry": 863, "common": 864, "denominator": 865, "lewinsky": 866, "low": 867, "monica": 868, "oh": 869, "sawyer": 870, "art": 871, "presley": 872, "soul": 873, "actually": 874, "balance": 875, "drummer": 876, "ringo": 877, "chronic": 878, "many": 879, "neighborhood": 880, "off-": 881, "putting": 882, "record": 883, "street": 884, "chihuahuas": 885, "compare": 886, "dog": 887, "miniature": 888, "wo": 889, "contest": 890, "contract": 891, "25": 892, "age": 893, "already": 894, "pretty": 895, "reason": 896, "set": 897, "demeanor": 898, "fifteen": 899, "fourteen": 900, "notice": 901, "significant": 902, "start": 903, "ali": 904, "unbelievable": 905, "template": 906, "code": 907, "language": 908, "person": 909, "serious": 910, "switch": 911, "switching": 912, "die": 913, "colleague": 914, "obviously": 915, "nothing": 916, "realize": 917, "sexuality": 918, "obsessive": 919, "adjust": 920, "history": 921, "structure": 922, "ago": 923, "eduard": 924, "georgia": 925, "youtube": 926, "inform": 927, "extent": 928, "opposite": 929, "guy": 930, "trump": 931, "degree": 932, "motivate": 933, "nth": 934, "suppose": 935, "2013": 936, "politic": 937, "st": 938, "crazy": 939, "hand": 940, "hey": 941, "listen": 942, "medium": 943, "politician": 944, "therefore": 945, "thing": 946, "powerful": 947, "able": 948, "notion": 949, "nurse": 950, "putin": 951, "shoulder": 952, "stand": 953, "long": 954, "lose": 955, "proposition": 956, "run": 957, "develop": 958, "gingrich": 959, "lifetime": 960, "thinking": 961, "couric": 962, "fluff": 963, "piece": 964, "showcase": 965, "desk": 966, "land": 967, "states": 968, "trouble": 969, "united": 970, "world": 971, "clean": 972, "favorite": 973, "housewives": 974, "metaphor": 975, "shop": 976, "tv": 977, "warring": 978, "instead": 979, "portfolio": 980, "anchor": 981, "display": 982, "later": 983, "o'reilly": 984, "temper": 985, "viral": 986, "courage": 987, "employee": 988, "exhibit": 989, "fox": 990, "gloria": 991, "male": 992, "news": 993, "conservative": 994, "crosstalk": 995, "manhattan": 996, "upper": 997, "wound": 998, "interaction": 999, "appreciation": 1000, "engage": 1001, "institution": 1002, "scaramucci": 1003, "anthony": 1004, "difference": 1005, "move": 1006, "sean": 1007, "spicer": 1008, "visible": 1009, "boyd": 1010, "gut": 1011, "manner": 1012, "agenda": 1013, "ambitious": 1014, "campaign": 1015, "expand": 1016, "overtime": 1017, "systematically": 1018, "four": 1019, "frustrating": 1020, "megyn": 1021, "morning": 1022, "trait": 1023, "defense": 1024, "high": 1025, "mechanism": 1026, "school": 1027, "brendan": 1028, "ha": 1029, "instance": 1030, "question": 1031, "specifically": 1032, "yeah": 1033, "actor": 1034, "author": 1035, "forecaster": 1036, "weather": 1037, "everybody": 1038, "il": 1039, "mooche": 1040, "anybody": 1041, "cultive": 1042, "daughter": 1043, "laura": 1044, "press": 1045, "profile": 1046, "taboo": 1047, "absolutely": 1048, "true": 1049, "akins": 1050, "angeles": 1051, "bill": 1052, "los": 1053, "lumi": 1054, "phony": 1055, "demonic": 1056, "denounce": 1057, "liar": 1058, "mental": 1059, "shortcoming": 1060, "brian": 1061, "dave": 1062, "ironic": 1063, "lamb": 1064, "player": 1065, "power": 1066, "regard": 1067, "thomason": 1068, "week": 1069, "cheney": 1070, "cold": 1071, "wyoming": 1072, "convention": 1073, "stay": 1074, "ann": 1075, "burns": 1076, "coulter": 1077, "combination": 1078, "assess": 1079, "collection": 1080, "essay": 1081, "fascinating": 1082, "liberal": 1083, "various": 1084, "flexibility": 1085, "grace": 1086, "shin": 1087, "strength": 1088, "interview": 1089, "base": 1090, "chapter": 1091, "every": 1092, "unique": 1093, "hundred": 1094, "currin": 1095, "mr": 1096, "provocative": 1097, "mask": 1098, "persona": 1099, "attract": 1100, "major": 1101, "moment": 1102, "russ": 1103, "polish": 1104, "experiment": 1105, "judgment": 1106, "mom": 1107, "motor": 1108, "winfrey": 1109, "gwaine": 1110, "mine": 1111, "um": 1112, "credential": 1113, "frequently": 1114, "provide": 1115, "spouse": 1116, "warmth": 1117, "comedy": 1118, "window": 1119, "delightful": 1120, "miser": 1121, "overargumentative": 1122, "physically": 1123, "unattractive": 1124, "800": 1125, "989-talk": 1126, "ad": 1127, "background": 1128, "completely": 1129, "john": 1130, "soundbite": 1131, "awe": 1132, "kid": 1133, "mellow": 1134, "shuck": 1135, "dissolve": 1136, "espn": 1137, "1computer": 1138, "ghiatry-": 1139, "abashidze": 1140, "paranoid": 1141, "fandom": 1142, "national": 1143, "affectionate": 1144, "box": 1145, "cat": 1146, "litter": 1147, "consistent": 1148, "songwriting": 1149, "translate": 1150, "concierge": 1151, "definitely": 1152, "ferro": 1153, "fescu": 1154, "worry": 1155, "individual": 1156, "mixed": 1157, "soup": 1158, "economy": 1159, "iraq": 1160, "debate": 1161, "three": 1162, "fighter": 1163, "nt": 1164, "altruistic": 1165, "eccentric": 1166, "jong": 1167, "dean": 1168, "media": 1169, "fit": 1170, "opportunity": 1171, "overcome": 1172, "bowls": 1173, "blitzer": 1174, "capitol": 1175, "guess": 1176, "hill": 1177, "judy": 1178, "lbj": 1179, "speaks": 1180, "volume": 1181, "woodruff": 1182, "zahn": 1183, "dark": 1184, "detect": 1185, "nancy": 1186, "liability": 1187, "motivation": 1188, "romney": 1189, "aggressive": 1190, "control": 1191, "demon": 1192, "inside": 1193, "stress": 1194, "tylar": 1195, "violent": 1196, "whole": 1197, "ama": 1198, "amilya": 1199, "antonetti": 1200, "ceo": 1201, "entrepreneur": 1202, "productions": 1203, "brassy": 1204, "dna": 1205, "irreverent": 1206, "mallory": 1207, "murphy": 1208, "opt": 1209, "visit": 1210, "voiceover": 1211, "comfortable": 1212, "entire": 1213, "frank": 1214, "jon": 1215, "yack": 1216, "car": 1217, "addictive": 1218, "avoid": 1219, "benzodiazepine": 1220, "general": 1221, "knowledge": 1222, "send": 1223, "specialist": 1224, "houston": 1225, "miss": 1226, "face": 1227, "runway": 1228, "walk": 1229, "ca": 1230, "graft": 1231, "rusty": 1232, "literally": 1233, "nbc": 1234, "generally": 1235, "rarely": 1236, "referendum": 1237, "sir": 1238, "sit": 1239, "bissinger": 1240, "kilmeade": 1241, "90": 1242, "percent": 1243, "shoe": 1244, "diagnosis": 1245, "disorder": 1246, "groundwork": 1247, "histrionic": 1248, "jerry": 1249, "lawyer": 1250, "lay": 1251, "sandusky": 1252, "allege": 1253, "groom": 1254, "prosecutor": 1255, "letter": 1256, "argue": 1257, "excuse": 1258, "fire": 1259, "neuron": 1260, "second": 1261, "sexual": 1262, "somehow": 1263, "care": 1264, "performance": 1265, "sudden": 1266, "ground": 1267, "lie": 1268, "interest": 1269, "predatory": 1270, "manifest": 1271, "apparent": 1272, "better": 1273, "folk": 1274, "paul": 1275, "ruling": 1276, "callan": 1277, "complete": 1278, "past": 1279, "academy": 1280, "accord": 1281, "borderline": 1282, "diagnose": 1283, "lawsuit": 1284, "leave": 1285, "chimp": 1286, "expert": 1287, "zarrella": 1288, "benefit": 1289, "doubt": 1290, "dependent": 1291, "de": 1292, "tour": 1293, "ancestor": 1294, "happen": 1295, "roughly": 1296, "indulge": 1297, "wish": 1298, "humble": 1299, "pose": 1300, "ok": 1301, "creator": 1302, "analyze": 1303, "observe": 1304, "room": 1305, "weirdness": 1306, "coincidence": 1307, "pure": 1308, "lerer": 1309, "advice": 1310, "objective": 1311, "beck": 1312, "childhood": 1313, "shape": 1314, "tough": 1315, "claim": 1316, "deep": 1317, "investigation": 1318, "tango": 1319, "website": 1320, "poise": 1321, "polished": 1322, "professional": 1323, "wherever": 1324, "100": 1325, "donald": 1326, "climate": 1327, "charm": 1328, "ant": 1329, "china": 1330, "diplomat": 1331, "hot": 1332, "use": 1333, "disturb": 1334, "jenna": 1335, "joel": 1336, "tom": 1337, "entirely": 1338, "handsome": 1339, "evaluate": 1340, "interested": 1341, "process": 1342, "shall": 1343, "tower": 1344, "vetting": 1345, "sound": 1346, "command": 1347, "nuclear": 1348, "woman": 1349, "everyday": 1350, "pivot": 1351, "principle": 1352, "substance": 1353, "inaudible": 1354, "away": 1355, "assessment": 1356, "fbi": 1357, "panther": 1358, "party": 1359, "sober": 1360, "presidency": 1361, "thread": 1362, "throughout": 1363, "unlikable": 1364, "wise": 1365, "palette": 1366, "shame": 1367, "stuck": 1368, "home": 1369, "broad": 1370, "khrushchev": 1371, "mao": 1372, "stalin": 1373, "bizarre": 1374, "congratulate": 1375, "graciously": 1376, "transformation": 1377, "winner": 1378, "personal": 1379, "unfortunately": 1380, "multiple": 1381, "disrespect": 1382, "disruptor": 1383, "game": 1384, "gon": 1385, "na": 1386, "matter": 1387, "oppose": 1388, "baldwin": 1389, "chat": 1390, "immediate": 1391, "interpretation": 1392, "vickers": 1393, "visceral": 1394, "without": 1395, "next": 1396, "bravado": 1397, "laugh": 1398, "barack": 1399, "disagree": 1400, "obama": 1401, "optimistic": 1402, "alcoholic": 1403, "cruz": 1404, "lime": 1405, "marco": 1406, "mock": 1407, "rubio": 1408, "state": 1409, "exact": 1410, "perfect": 1411, "tolerance": 1412, "zero": 1413, "sure": 1414, "contradiction": 1415, "striking": 1416, "weakness": 1417, "perspective": 1418, "bureaucratic": 1419, "corrupt": 1420, "fight": 1421, "incestuous": 1422, "washington": 1423, "willing": 1424, "concern": 1425, "transplant": 1426, "coming": 1427, "beautiful": 1428, "idea": 1429, "karma": 1430, "raise": 1431, "alex": 1432, "ridiculous": 1433, "chance": 1434, "calculated": 1435, "sin": 1436, "pope": 1437, "flowery": 1438, "poetic": 1439, "erica": 1440, "impression": 1441, "brain": 1442, "cruel": 1443, "eric": 1444, "o'toole": 1445, "rambling": 1446, "sadistic": 1447, "signal": 1448, "category": 1449, "cross": 1450, "path": 1451, "sometimes": 1452, "active": 1453, "church": 1454, "community": 1455, "dynamic": 1456, "symphony": 1457, "volunteer": 1458, "cake": 1459, "concerned": 1460, "mix": 1461, "food": 1462, "liquid": 1463, "trucker": 1464, "phillips": 1465, "wallace": 1466, "schizophrenia": 1467, "stuff": 1468, "final": 1469, "voter": 1470, "compliment": 1471, "ruin": 1472, "announcement": 1473, "spirit": 1474, "chelsea": 1475, "kindness": 1476, "pick": 1477, "alive": 1478, "read": 1479, "aide": 1480, "arguably": 1481, "influential": 1482, "public": 1483, "rove": 1484, "beginning": 1485, "characteristic": 1486, "conan": 1487, "five": 1488, "noah": 1489, "feeding": 1490, "husbands": 1491, "proper": 1492, "schlessinger": 1493, "bolton": 1494, "delay": 1495, "actual": 1496, "associate": 1497, "pressured": 1498, "talent": 1499, "biological": 1500, "component": 1501, "psychologist": 1502, "temperament": 1503, "tend": 1504, "hardiness": 1505, "lens": 1506, "flamboyant": 1507, "turn": 1508, "classical": 1509, "sociopathic": 1510, "aside": 1511, "george": 1512, "oprah": 1513, "casualty": 1514, "challenger": 1515, "christa": 1516, "effervescent": 1517, "mcauliffe": 1518, "shuttle": 1519, "breeze": 1520, "classmate": 1521, "elite": 1522, "excel": 1523, "faster": 1524, "harvard": 1525, "impress": 1526, "robert": 1527, "assume": 1528, "basically": 1529, "laci": 1530, "citrus": 1531, "county": 1532, "dawsy": 1533, "florida": 1534, "jeff": 1535, "sheriff": 1536, "validate": 1537, "coincidently": 1538, "criminal": 1539, "salary": 1540, "unlisted": 1541, "afterwards": 1542, "dramatically": 1543, "gibbons": 1544, "injury": 1545, "moos": 1546, "survive": 1547, "university": 1548, "ahead": 1549, "elbow": 1550, "malign": 1551, "newspaper": 1552, "spotlight": 1553, "casey": 1554, "deejay": 1555, "dees": 1556, "disc": 1557, "faceless": 1558, "jockey": 1559, "kasem": 1560, "mass": 1561, "replace": 1562, "rick": 1563, "wolfman": 1564, "brucie": 1565, "cousin": 1566, "emotion": 1567, "morrow": 1568, "properly": 1569, "5": 1570, "benson": 1571, "californias": 1572, "classic": 1573, "headphone": 1574, "hit": 1575, "jack": 1576, "joe": 1577, "klos": 1578, "rock": 1579, "southern": 1580, "unceremoniously": 1581, "vargas": 1582, "void": 1583, "assassinate": 1584, "impeccable": 1585, "slander": 1586, "biz": 1587, "brener": 1588, "collins": 1589, "kenneth": 1590, "phil": 1591, "appetite": 1592, "scooter": 1593, "sluggish": 1594, "viles": 1595, "career": 1596, "deny": 1597, "shake": 1598, "burton": 1599, "drug": 1600, "heavy": 1601, "nine": 1602, "prescription": 1603, "toward": 1604, "close": 1605, "lucky": 1606, "nominate": 1607, "distinctive": 1608, "conference": 1609, "eisenhower": 1610, "disagreement": 1611, "essentially": 1612, "lurk": 1613, "psychopath": 1614, "sociopath": 1615, "chase": 1616, "iran": 1617, "mullah": 1618, "zia": 1619, "create": 1620, "antisocial": 1621, "escape": 1622, "impulsive": 1623, "suggest": 1624, "wampler": 1625, "anastasi": 1626, "accuser": 1627, "jane": 1628, "malave": 1629, "check": 1630, "hospital": 1631, "program": 1632, "special": 1633, "speigel": 1634, "teach": 1635, "fuel": 1636, "revenge": 1637, "sign": 1638, "victim": 1639, "authentic": 1640, "quickly": 1641, "spiegel": 1642, "usually": 1643, "patient": 1644, "unaware": 1645, "conspiracy": 1646, "janes": 1647, "firm": 1648, "schedule": 1649, "patronize": 1650, "hug": 1651, "kiss": 1652, "incarcerate": 1653, "private": 1654, "shelter": 1655, "anyone": 1656, "cage": 1657, "cujo": 1658, "hoda": 1659, "motive": 1660, "banter": 1661, "episode": 1662, "favreau": 1663, "share": 1664, "unscript": 1665, "suffer": 1666, "acting": 1667, "f": 1668, "imitate": 1669, "travolta": 1670, "brazen": 1671, "flaw": 1672, "idiosyncratic": 1673, "judgmental": 1674, "ruthlessly": 1675, "unpredictable": 1676, "hawks": 1677, "hitchcock": 1678, "uneasy": 1679, "volatile": 1680, "enhance": 1681, "furniture": 1682, "60": 1683, "goodness": 1684, "immeasurable": 1685, "astrological": 1686, "cynical": 1687, "disclaimer": 1688, "normal": 1689, "stranger": 1690, "detractor": 1691, "levine": 1692, "warner": 1693, "civil": 1694, "holiday": 1695, "kurt": 1696, "movement": 1697, "renton": 1698, "analyst": 1699, "crucial": 1700, "leusha": 1701, "peter": 1702, "case": 1703, "current": 1704, "decisive": 1705, "custom": 1706, "characterological": 1707, "respond": 1708, "comic": 1709, "critic": 1710, "independent": 1711, "satisfying": 1712, "keaton": 1713, "representation": 1714, "assault": 1715, "drive": 1716, "enormous": 1717, "fashionable": 1718, "vehicle": 1719, "worrying": 1720, "audience": 1721, "dazzle": 1722, "distract": 1723, "fly": 1724, "theatrical": 1725, "analytical": 1726, "creative": 1727, "poet": 1728, "scientific": 1729, "unite": 1730, "backstage": 1731, "minority": 1732, "sadness": 1733, "screen": 1734, "war": 1735, "magnetic": 1736, "spell": 1737, "fiction": 1738, "tale": 1739, "group": 1740, "jirga": 1741, "loya": 1742, "meeting": 1743, "order": 1744, "understanding": 1745, "feeling": 1746, "gather": 1747, "location": 1748, "exhibitionistic": 1749, "anderson": 1750, "fhm": 1751, "pamela": 1752, "thousand": 1753, "wide": 1754, "talkative": 1755, "pompous": 1756, "cable": 1757, "network": 1758, "watch": 1759, "ability": 1760, "athletic": 1761, "inherit": 1762, "carry": 1763, "eight": 1764, "flag": 1765, "indeed": 1766, "olympic": 1767, "arafat": 1768, "chairman": 1769, "snow": 1770, "tick": 1771, "dominant": 1772, "10ks": 1773, "limit": 1774, "marathon": 1775, "push": 1776, "camp": 1777, "thank": 1778, "death": 1779, "if-": 1780, "verge": 1781, "who-": 1782, "crude": 1783, "howard": 1784, "humor": 1785, "stern": 1786, "vulgar": 1787, "whose": 1788, "evidence": 1789, "jealousy": 1790, "proof": 1791, "jennings": 1792, "gramm": 1793, "mondale": 1794, "walter": 1795, "course": 1796, "preserve": 1797, "struggle": 1798, "fore": 1799, "potential": 1800, "involve": 1801, "science": 1802, "head": 1803, "lifeless": 1804, "plop": 1805, "and-": 1806, "anyone-": 1807, "hat": 1808, "alone": 1809, "charming": 1810, "intellect": 1811, "petty": 1812, "slip": 1813, "trust": 1814, "undo": 1815, "caretaker": 1816, "original": 1817, "theory": 1818, "unintelligible": 1819, "97": 1820, "shawn": 1821, "homosexuality": 1822, "psychiatrist": 1823, "socarides": 1824, "symptom": 1825, "underlying": 1826, "hart": 1827, "heather": 1828, "journalist": 1829, "rivera": 1830, "late": 1831, "liplock": 1832, "report": 1833, "griffith": 1834, "melanie": 1835, "article": 1836, "lesbian": 1837, "magazine": 1838, "introvert": 1839, "chen": 1840, "eve": 1841, "nicole": 1842, "perfectionist": 1843, "attorneys-": 1844, "impact": 1845, "mailer": 1846, "norman": 1847, "similar": 1848, "be-": 1849, "foreper-": 1850, "foreperson": 1851, "jeffrey": 1852, "know-": 1853, "toobin": 1854, "adrian": 1855, "air": 1856, "cronauer": 1857, "leon": 1858, "deborah": 1859, "marchini": 1860, "abraham": 1861, "either": 1862, "lincoln": 1863, "slavery": 1864, "clear": 1865, "perot": 1866, "powell": 1867, "clark": 1868, "contrary": 1869, "demonstrate": 1870, "marcia": 1871, "combat": 1872, "formula": 1873, "journalism": 1874, "budget": 1875, "slash": 1876, "drain": 1877, "individuality": 1878, "town": 1879, "critical": 1880, "simple": 1881, "skirt": 1882, "guide": 1883, "luck": 1884, "exploit": 1885, "garner": 1886, "publicity": 1887, "a-": 1888, "him-": 1889, "whatev": 1890, "-with": 1891, "donaldson": 1892, "gary": 1893, "sam": 1894, "birch": 1895, "freedom": 1896, "kate": 1897, "diversity": 1898, "guitar": 1899, "hotshot": 1900, "lick": 1901, "necessarily": 1902, "watt": 1903, "wrestle": 1904, "dish": 1905, "infection": 1906, "neat": 1907, "petri": 1908, "spore": 1909, "icon": 1910, "cultivate": 1911, "slightly": 1912, "bing": 1913, "crosby": 1914, "disappear": 1915, "excerpt": 1916, "natured": 1917, "relaxed": 1918, "stamberg": 1919, "banana": 1920, "eat": 1921, "train": 1922, "troubled": 1923, "befitting": 1924, "bench": 1925, "catcher": 1926, "cincinnati": 1927, "fame": 1928, "hall": 1929, "member": 1930, "reds": 1931, "tradition": 1932, "endearing": 1933, "facet": 1934, "donahue": 1935, "since": 1936, "sweeney": 1937, "firmly": 1938, "moral": 1939, "stick": 1940, "vision": 1941, "degrade": 1942, "unjust": 1943, "uplift": 1944, "newt": 1945, "velvety": 1946, "hyde": 1947, "jekyll": 1948, "conflict": 1949, "simpson": 1950, "24": 1951, "clinton": 1952, "product": 1953, "allen": 1954, "expression": 1955, "woody": 1956, "daniel": 1957, "hansen": 1958, "liane": 1959, "wolff": 1960, "positive": 1961, "compulsive": 1962, "discipline": 1963, "wrong": 1964, "curious": 1965, "exchange": 1966, "half": 1967, "psyche": 1968, "week-": 1969, "16": 1970, "duke": 1971, "patty": 1972, "series": 1973, "anna": 1974, "descent": 1975, "hell": 1976, "ironically": 1977, "attitude": 1978, "dad": 1979, "drastically": 1980, "jan": 1981, "scott": 1982, "camille": 1983, "date": 1984, "irrational": 1985, "paglia": 1986, "criticism": 1987, "fed": 1988, "trelford": 1989, "breath": 1990, "breezy": 1991, "fresh": 1992, "palace": 1993, "stuffy": 1994, "cause": 1995, "diamond": 1996, "desperately": 1997, "limbaugh": 1998, "mostly": 1999, "nice": 2000, "rush": 2001, "adolescence": 2002, "adulthood": 2003, "allow": 2004, "intact": 2005, "transition": 2006, "fabulously": 2007, "magnus": 2008, "divided": 2009, "mayer": 2010, "minds": 2011, "satan": 2012, "studies": 2013, "english": 2014, "lump": 2015, "plain": 2016, "tumor": 2017, "89": 2018, "briefly": 2019, "katherine": 2020, "seven": 2021, "accept": 2022, "brother": 2023, "clinically": 2024, "attack": 2025, "brutal": 2026, "development": 2027, "protect": 2028, "protection": 2029, "perhaps": 2030, "vacuum": 2031, "18": 2032, "accuse": 2033, "consent": 2034, "sex": 2035, "advantage": 2036, "hearing": 2037, "preliminary": 2038, "testify": 2039, "warn": 2040, "exist": 2041, "jenny": 2042, "somewhere": 2043, "19": 2044, "overeating": 2045, "pam": 2046, "mention": 2047, "mpd": 2048, "15": 2049, "figure": 2050, "honey": 2051, "beforehand": 2052, "plus": 2053, "continual": 2054, "deal": 2055, "react": 2056, "adams": 2057, "cindy": 2058, "columnist": 2059, "experience": 2060, "learn": 2061, "roommate": 2062, "several": 2063, "talker": 2064, "showy": 2065, "asset": 2066, "button": 2067, "dick": 2068, "sexy": 2069, "skating": 2070, "bandstand": 2071, "outside": 2072, "colorful": 2073, "ed": 2074, "mind": 2075, "wicker": 2076, "chemistry": 2077, "something-": 2078, "nowadays": 2079, "rally": 2080, "round": 2081, "christopher": 2082, "flashy": 2083, "mcwethy": 2084, "vs": 2085, "lila": 2086, "250,000": 2087, "familiar": 2088, "filipinos": 2089, "garfield": 2090, "hawaii": 2091, "kndi": 2092, "laso": 2093, "rest": 2094, "muscovite": 2095, "posner": 2096, "soviet": 2097, "vladimir": 2098, "delve": 2099, "evil": 2100, "intrigue": 2101, "ruth": 2102, "engineer": 2103, "sullen": 2104, "deftness": 2105, "ideally": 2106, "intelligence": 2107, "negotiating": 2108, "softness": 2109, "suit": 2110, "superb": 2111, "brown": 2112, "kinsley": 2113, "theorize": 2114, "telegenic": 2115, "impossible": 2116, "dirty": 2117, "not-": 2118, "opposition": 2119, "redefine": 2120, "research": 2121, "trick": 2122, "composite": 2123, "apart": 2124, "mcnamara": 2125, "cam": 2126, "circle": 2127, "controversial": 2128, "hong": 2129, "kong": 2130, "wang": 2131, "contempt": 2132, "defrank": 2133, "edward": 2134, "handler": 2135, "electable": 2136, "used": 2137, "involvement": 2138, "possibility": 2139, "gov": 2140, "12": 2141, "republican": 2142, "admiral": 2143, "expect": 2144, "may-": 2145, "might": 2146, "stockdale": 2147, "brittle": 2148, "helmsley": 2149, "june": 2150, "ought": 2151, "sonya": 2152, "michael": 2153, "rodin": 2154, "search": 2155, "support": 2156, "surprisingly": 2157, "marsh": 2158, "addicted": 2159, "influence": 2160, "mainly": 2161, "religious": 2162, "impressive": 2163, "mixture": 2164, "outstanding": 2165, "overwhelm": 2166, "belief": 2167, "fundamental": 2168, "oratory": 2169, "schizoid": 2170, "henninger": 2171, "mere": 2172, "stuart": 2173, "varney": 2174, "1femal": 2175, "contestant-": 2176, "intentionally": 2177, "carter": 2178, "channel": 2179, "lifelong": 2180, "kardashian": 2181, "legend": 2182, "alpha": 2183, "enthusiasm": 2184, "thriving": 2185, "extra": 2186, "atm": 2187, "envelope": 2188, "extension": 2189, "forth": 2190, "brooklyn": 2191, "grandmother": 2192, "cognition": 2193, "treatment": 2194, "kill": 2195, "passive": 2196, "prosecute": 2197, "u": 2198, "1fan": 2199, "2-": 2200, "jamie-": 2201, "red": 2202, "vienna": 2203, "alike": 2204, "god": 2205, "growth": 2206, "perceive": 2207, "upward": 2208, "bobbys": 2209, "unpleasant": 2210, "define": 2211, "matthews": 2212, "fairly": 2213, "npr": 2214, "smiley": 2215, "tavis": 2216, "flatow": 2217, "viewpoint": 2218, "reflect": 2219, "wedding": 2220, "chantilly": 2221, "kathy": 2222, "masked": 2223, "wild": 2224, "detail": 2225, "gear": 2226, "mentally": 2227, "tweet": 2228, "extreme": 2229, "possible": 2230, "rating": 2231, "habitual": 2232, "bunch": 2233, "charlotte": 2234, "leah": 2235, "master": 2236, "retire": 2237, "rosa": 2238, "sandra": 2239, "sergeant": 2240, "mitt": 2241, "remarkable": 2242, "sector": 2243, "amazing": 2244, "vibrant": 2245, "typical": 2246, "23": 2247, "abc": 2248, "barbara": 2249, "night": 2250, "sullivan": 2251, "walters": 2252, "conrad": 2253, "lauren": 2254, "daker": 2255, "disturbed": 2256, "enjoy": 2257, "lottie": 2258, "threat": 2259, "mcdonnell": 2260, "buffalo": 2261, "calculation": 2262, "conviction": 2263, "democrats": 2264, "district": 2265, "divide": 2266, "evenly": 2267, "kemp": 2268, "republicans": 2269, "stage": 2270, "anyway": 2271, "neither": 2272, "partner": 2273, "pinsky": 2274, "zach": 2275, "battery": 2276, "memory": 2277, "comedian": 2278, "fugelsang": 2279, "nadia": 2280, "communicate": 2281, "commission": 2282, "consider": 2283, "forward": 2284, "moderator": 2285, "schieffer": 2286, "dinner": 2287, "white": 2288, "huge": 2289, "likability": 2290, "foreign": 2291, "frankly": 2292, "vote": 2293, "cite": 2294, "rice": 2295, "writer": 2296, "body": 2297, "syrians": 2298, "transitional": 2299, "andrew": 2300, "announce": 2301, "apparently": 2302, "blogger": 2303, "cooper": 2304, "email": 2305, "gay": 2306, "orientation": 2307, "attention": 2308, "26,000": 2309, "emanuel": 2310, "karen": 2311, "lewis": 2312, "rahm": 2313, "learner": 2314, "available": 2315, "cache": 2316, "loner": 2317, "readily": 2318, "recluse": 2319, "weapon": 2320, "clintonites": 2321, "hillary": 2322, "authenticity": 2323, "identical": 2324, "twin": 2325, "caring": 2326, "genuine": 2327, "decide": 2328, "lean": 2329, "sharp": 2330, "eventually": 2331, "initial": 2332, "job": 2333, "jp": 2334, "local": 2335, "charisma": 2336, "predator": 2337, "alligator": 2338, "supercharge": 2339, "traumatize": 2340, "overwhelmingly": 2341, "primary": 2342, "heck": 2343, "infectious": 2344, "franklin": 2345, "belie": 2346, "congenial": 2347, "spot": 2348, "uncanny": 2349, "willett": 2350, "ambassador": 2351, "sybil": 2352, "tortured": 2353, "entertainment": 2354, "generous": 2355, "parade": 2356, "profit": 2357, "recreate": 2358, "deeply": 2359, "neurotic": 2360, "court": 2361, "determine": 2362, "atomic": 2363, "bomb": 2364, "essential": 2365, "pinkerton": 2366, "partly": 2367, "cattle": 2368, "trade": 2369, "jason": 2370, "marriage": 2371, "morrison": 2372, "hurt": 2373, "palin": 2374, "sarah": 2375, "club": 2376, "faces": 2377, "dissociative": 2378, "identity": 2379, "illness": 2380, "rare": 2381, "walker": 2382, "alter": 2383, "alternate": 2384, "football": 2385, "decade": 2386, "deceit": 2387, "function": 2388, "measurable": 2389, "surprising": 2390, "conservatism": 2391, "defect": 2392, "flight": 2393, "reality": 2394, "dole": 2395, "rudin": 2396, "leader": 2397, "separate": 2398, "outspoken": 2399, "gifford": 2400, "education": 2401, "summers": 2402, "birnbaum": 2403, "fred": 2404, "amani": 2405, "chideya": 2406, "indecision": 2407, "largely": 2408, "safe": 2409, "onto": 2410, "oversight": 2411, "responsibility": 2412, "barrier": 2413, "chain": 2414, "erosive": 2415, "lyndon": 2416, "mcveigh": 2417, "timothy": 2418, "considerable": 2419, "door": 2420, "goofy": 2421, "specific": 2422, "evelyn": 2423, "mays": 2424, "reindeer": 2425, "inject": 2426, "bathroom": 2427, "clue": 2428, "confess": 2429, "photograph": 2430, "snoop": 2431, "across": 2432, "fear": 2433, "nightmare": 2434, "terrible": 2435, "artist": 2436, "botticelli": 2437, "gradual": 2438, "introduction": 2439, "painting": 2440, "sandro": 2441, "sexiness": 2442, "cialdini": 2443, "kennedy": 2444, "release": 2445, "statement": 2446, "caustic": 2447, "curmudgeonly": 2448, "kingsley": 2449, "satire": 2450, "wit": 2451, "demand": 2452, "miles": 2453, "muldaur": 2454, "organization": 2455, "chemically": 2456, "depression": 2457, "fascinated": 2458, "astonishment": 2459, "uncharacteristic": 2460, "violence": 2461, "afflict": 2462, "boundary": 2463, "distasteful": 2464, "obsequious": 2465, "sincere": 2466, "striving": 2467, "physical": 2468, "size": 2469, "hilarious": 2470, "jimmy": 2471, "film": 2472, "massachusetts": 2473, "admittedly": 2474, "obvious": 2475, "reach": 2476, "sport": 2477, "truly": 2478, "commentator": 2479, "reporter": 2480, "consensus": 2481, "intersect": 2482, "anymore": 2483, "shadow": 2484, "1930": 2485, "celebrated": 2486, "camera": 2487, "instinct": 2488, "photographer": 2489, "al": 2490, "hunt": 2491, "miller": 2492, "november": 2493, "senate": 2494, "bauer": 2495, "carlson": 2496, "moderate": 2497, "description": 2498, "exceptional": 2499, "extraordinary": 2500, "forget": 2501, "information": 2502, "minister": 2503, "l": 2504, "2000": 2505, "gore": 2506, "leading": 2507, "secretary": 2508, "warren": 2509, "finally": 2510, "privately": 2511, "randolph": 2512, "jennifer": 2513, "lopez": 2514, "compelling": 2515, "exceed": 2516, "expectation": 2517, "unidentified": 2518, "milbank": 2519, "society": 2520, "however": 2521, "blend": 2522, "early": 2523, "mould": 2524, "reith": 2525, "nyerere": 2526, "ass": 2527, "erratic": 2528, "occasional": 2529, "pain": 2530, "fifty": 2531, "patronage": 2532, "sinatra": 2533, "determination": 2534, "immodest": 2535, "incredible": 2536, "deluise": 2537, "dom": 2538, "picture": 2539, "reynold": 2540, "sidekick": 2541, "vastly": 2542, "rufus": 2543, "sensitivity": 2544, "imperative": 2545, "liberalism": 2546, "tension": 2547, "economic": 2548, "radical": 2549, "rupture": 2550, "scarcity": 2551, "alien": 2552, "idleness": 2553, "plant": 2554, "government": 2555, "pressure": 2556, "westminster": 2557, "arise": 2558, "bias": 2559, "difficulty": 2560, "oracy": 2561, "perception": 2562, "pupil": 2563, "spoken": 2564, "\u2019": 2565, "behaviour": 2566, "beyond": 2567, "devil": 2568, "division": 2569, "modern": 2570, "psychoanalysis": 2571, "splitting": 2572, "curiosity": 2573, "direction": 2574, "enlighten": 2575, "object": 2576, "satisfy": 2577, "contact": 2578, "easily": 2579, "establish": 2580, "likely": 2581, "relate": 2582, "basic": 2583, "maslow": 2584, "motivational": 2585, "closely": 2586, "whoever": 2587, "authority": 2588, "bone": 2589, "impose": 2590, "possess": 2591, "sombre": 2592, "unassailable": 2593, "unexpectedly": 2594, "consist": 2595, "innocuous": 2596, "dustpan": 2597, "howl": 2598, "suitcase": 2599, "sweep": 2600, "trace": 2601, "imagination": 2602, "hearth": 2603, "imprint": 2604, "space": 2605, "developmentally": 2606, "gain": 2607, "infant": 2608, "progress": 2609, "slow": 2610, "autistic": 2611, "epileptic": 2612, "example": 2613, "fragile": 2614, "lobe": 2615, "syndrome": 2616, "temporal": 2617, "beijing": 2618, "brink": 2619, "campus": 2620, "reminder": 2621, "\u2018": 2622, "downside": 2623, "17": 2624, "arrive": 2625, "conscious": 2626, "rescue": 2627, "tribute": 2628, "indication": 2629, "knit": 2630, "machine": 2631, "worker": 2632, "section": 2633, "appreciative": 2634, "generosity": 2635, "strongly": 2636, "elderly": 2637, "knot": 2638, "qualified": 2639, "standing": 2640, "behavioural": 2641, "cognitive": 2642, "emotional": 2643, "erode": 2644, "event": 2645, "gradually": 2646, "impairment": 2647, "loss": 2648, "previous": 2649, "recent": 2650, "accompany": 2651, "anxiety": 2652, "initiative": 2653, "restlessness": 2654, "spontaneity": 2655, "tea": 2656, "carer": 2657, "continuum": 2658, "residential": 2659, "maintain": 2660, "memento": 2661, "souvenir": 2662, "compose": 2663, "recognise": 2664, "response": 2665, "illustrate": 2666, "julia": 2667, "build": 2668, "building": 2669, "complexity": 2670, "construct": 2671, "storey": 2672, "tall": 2673, "makeup": 2674, "brief": 2675, "span": 2676, "except": 2677, "occasionally": 2678, "phyllis": 2679, "supermarket": 2680, "undergo": 2681, "adult": 2682, "arouse": 2683, "devastatingly": 2684, "manipulative": 2685, "negative": 2686, "reaction": 2687, "aircraft": 2688, "along": 2689, "naval": 2690, "pilot": 2691, "seat": 2692, "autogyro": 2693, "design": 2694, "meanwhile": 2695, "mickie": 2696, "parallel": 2697, "airfield": 2698, "crop": 2699, "disused": 2700, "perusal": 2701, "produce": 2702, "anthea": 2703, "fine": 2704, "hair": 2705, "turner": 2706, "regular": 2707, "twist": 2708, "communicative": 2709, "lifeworld": 2710, "accident": 2711, "outweigh": 2712, "relation": 2713, "address": 2714, "argument": 2715, "plekhanov": 2716, "causal": 2717, "defence": 2718, "discussion": 2719, "mode": 2720, "-lsb-": 2721, "-rsb-": 2722, "breaking": 2723, "rate": 2724, "responsible": 2725, "truce": 2726, "disparate": 2727, "equation": 2728, "tree": 2729, "animal": 2730, "incapable": 2731, "confusing": 2732, "direct": 2733, "entitle": 2734, "justice": 2735, "qualifier": 2736, "rawls": 2737, "retarded": 2738, "criterion": 2739, "einstein": 2740, "introduce": 2741, "settle": 2742, "status": 2743, "rightful": 2744, "earlier": 2745, "millennium": 2746, "ambition": 2747, "combine": 2748, "ruthlessness": 2749, "total": 2750, "tycoon": 2751, "decline": 2752, "nuance": 2753, "organisational": 2754, "setting": 2755, "inclined": 2756, "key": 2757, "sociologist": 2758, "whereas": 2759, "comment": 2760, "drama": 2761, "emphasis": 2762, "cup": 2763, "gray": 2764, "mountaineer": 2765, "muriel": 2766, "azhag": 2767, "immeasurably": 2768, "nagash": 2769, "1938": 2770, "arnold": 2771, "damascus": 2772, "document": 2773, "elders": 2774, "leese": 2775, "protocols": 2776, "road": 2777, "zion": 2778, "1933": 2779, "a.k": 2780, "alexander": 2781, "chesterton": 2782, "convince": 2783, "creed": 2784, "dundas": 2785, "fascist": 2786, "joyce": 2787, "mosley": 2788, "raven": 2789, "thomson": 2790, "william": 2791, "disproportionate": 2792, "locality": 2793, "prejudiced": 2794, "antic": 2795, "cajole": 2796, "crack": 2797, "encourage": 2798, "golf": 2799, "golfing": 2800, "joke": 2801, "lesson": 2802, "swing": 2803, "exacerbate": 2804, "price": 2805, "theorise": 2806, "mach": 2807, "osf/1": 2808, "rumour": 2809, "server": 2810, "single": 2811, "version": 2812, "dec": 2813, "svr4": 2814, "telecomms": 2815, "unix": 2816, "debut": 2817, "summertime": 2818, "expense": 2819, "obsession": 2820, "seek": 2821, "integral": 2822, "comdex": 2823, "concurrently": 2824, "ibm": 2825, "kernel": 2826, "microkernel": 2827, "os/2": 2828, "ps/2": 2829, "reward": 2830, "breed": 2831, "crufts": 2832, "pet": 2833, "collar": 2834, "occur": 2835, "thursday": 2836, "divinity": 2837, "naturally": 2838, "pervade": 2839, "turnip": 2840, "mars": 2841, "venue": 2842, "bond": 2843, "agreeable": 2844, "circumstance": 2845, "fix": 2846, "mutually": 2847, "health": 2848, "mobility": 2849, "brave": 2850, "tear": 2851, "mature": 2852, "strand": 2853, "bird": 2854, "fairness": 2855, "greatly": 2856, "compensate": 2857, "neatly": 2858, "cope": 2859, "longstanding": 2860, "pathological": 2861, "relative": 2862, "cosi": 2863, "habitat": 2864, "aix": 2865, "beta": 2866, "company": 2867, "os": 2868, "quarter": 2869, "ship": 2870, "third": 2871, "workplace": 2872, "envisage": 2873, "austin": 2874, "increase": 2875, "variety": 2876, "hint": 2877, "intrude": 2878, "thought": 2879, "bellamy": 2880, "gonzales": 2881, "intimidate": 2882, "merely": 2883, "tennis": 2884, "affairs": 2885, "bbc": 2886, "chair": 2887, "cosy": 2888, "editor": 2889, "johnston": 2890, "lacey": 2891, "norma": 2892, "resident": 2893, "aware": 2894, "decision": 2895, "disadvantage": 2896, "hiv": 2897, "educational": 2898, "sensory": 2899, "encounter": 2900, "unlikely": 2901, "obey": 2902, "psychology": 2903, "inherently": 2904, "attribute": 2905, "conception": 2906, "invest": 2907, "projection": 2908, "supreme": 2909, "endow": 2910, "gods": 2911, "hindu": 2912, "india": 2913, "composition": 2914, "judicial": 2915, "jury": 2916, "magistrate": 2917, "despite": 2918, "freddie": 2919, "survivor": 2920, "airline": 2921, "antigua": 2922, "liat": 2923, "prominent": 2924, "spokesman": 2925, "honour": 2926, "200": 2927, "44": 2928, "alan": 2929, "barry": 2930, "bart": 2931, "composer": 2932, "crematorium": 2933, "freeman": 2934, "lionel": 2935, "putney": 2936, "southwest": 2937, "vale": 2938, "parkinson": 2939, "crisis": 2940, "flair": 2941, "compulsion": 2942, "incline": 2943, "intimacy": 2944, "prevail": 2945, "yield": 2946, "method": 2947, "obsess": 2948, "project": 2949, "uncomfortable": 2950, "approve": 2951, "vincent": 2952, "repel": 2953, "boil": 2954, "manager": 2955, "quinn": 2956, "striker": 2957, "boot": 2958, "capable": 2959, "enfant": 2960, "magic": 2961, "manchester": 2962, "terrible\u2014": 2963, "troublemaker": 2964, "ipswich": 2965, "mcgiven": 2966, "mick": 2967, "successfully": 2968, "attend": 2969, "bowe": 2970, "climax": 2971, "newman": 2972, "programme": 2973, "sports": 2974, "voluble": 2975, "weekend": 2976, "motivator": 2977, "aloof": 2978, "graeme": 2979, "opinionated": 2980, "jealous": 2981, "lineker": 2982, "sooner": 2983, "taylor": 2984, "classroom": 2985, "defy": 2986, "expedient": 2987, "generality": 2988, "reduction": 2989, "tactic": 2990, "diane": 2991, "dodds": 2992, "gathering": 2993, "hunniford": 2994, "lord": 2995, "mayor": 2996, "nigel": 2997, "ulster": 2998, "destructive": 2999, "sneak": 3000, "tory": 3001, "advertising": 3002, "rise": 3003, "exactly": 3004, "lovingly": 3005, "stamp": 3006, "50": 3007, "discover": 3008, "parson": 3009, "village": 3010, "longer": 3011, "secular": 3012, "vicar": 3013, "ooze": 3014, "9": 3015, "8": 3016, "10": 3017, "behalf": 3018, "institute": 3019, "plea": 3020, "reiterate": 3021, "activity": 3022, "bank": 3023, "g": 3024, "boredom": 3025, "dissatisfaction": 3026, "duty": 3027, "evaluation": 3028, "grievance": 3029, "promotion": 3030, "source": 3031, "working": 3032, "respect": 3033, "aim": 3034, "bild": 3035, "daily": 3036, "germany": 3037, "krabbe": 3038, "station": 3039, "abnormality": 3040, "caesar": 3041, "characterise": 3042, "christ": 3043, "confucius": 3044, "hitler": 3045, "jesus": 3046, "julius": 3047, "demanding": 3048, "destruction": 3049, "herman": 3050, "snapshot": 3051, "ai": 3052, "bloody": 3053, "bugger": 3054, "lovely": 3055, "hardly": 3056, "wonder": 3057, "ball": 3058, "breakfast": 3059, "launch": 3060, "yesterday": 3061, "courteous": 3062, "exhilarating": 3063, "portray": 3064, "stepmother": 3065, "wicked": 3066, "bungalow": 3067, "mile": 3068, "reid": 3069, "commit": 3070, "constitute": 3071, "failure": 3072, "invasion": 3073, "seriously": 3074, "1995": 3075, "assure": 3076, "irb": 3077, "sarb": 3078, "saru": 3079, "unity": 3080, "popularity": 3081, "wednesday": 3082, "prince": 3083, "substitute": 3084, "sole": 3085, "benny": 3086, "intelligent": 3087, "mumbling": 3088, "opera": 3089, "portrait": 3090, "borg": 3091, "intimate": 3092, "jean": 3093, "luc": 3094, "poke": 3095, "strip": 3096, "wire": 3097, "italian": 3098, "affair": 3099, "executive": 3100, "howes": 3101, "league": 3102, "offiah": 3103, "rugby": 3104, "said": 3105, "goalscorer": 3106, "hero": 3107, "scorer": 3108, "soccer": 3109, "dunphy": 3110, "eamon": 3111, "international": 3112, "irish": 3113, "adherence": 3114, "calm": 3115, "conduct": 3116, "exterior": 3117, "jones": 3118, "recreation": 3119, "restrict": 3120, "difficult": 3121, "irritable": 3122, "trauma": 3123, "adoption": 3124, "fairy": 3125, "hardbitten": 3126, "heart": 3127, "steal": 3128, "sunny": 3129, "59": 3130, "bristol": 3131, "coma": 3132, "crash": 3133, "crowther": 3134, "frenchay": 3135, "leslie": 3136, "recover": 3137, "crime": 3138, "overnight": 3139, "senseless": 3140, "british": 3141, "dementia": 3142, "disease": 3143, "scientist": 3144, "contribute": 3145, "upon": 3146, "appropriately": 3147, "continuously": 3148, "counselling": 3149, "healthy": 3150, "fluctuate": 3151, "formative": 3152, "distress": 3153, "absolute": 3154, "concrete": 3155, "gall": 3156, "truth": 3157, "definition": 3158, "attempt": 3159, "debatable": 3160, "and/or": 3161, "conditioning": 3162, "environment": 3163, "purely": 3164, "differ": 3165, "freud": 3166, "extensively": 3167, "theorist": 3168, "concentric": 3169, "ring": 3170, "centre": 3171, "core": 3172, "effectively": 3173, "highly": 3174, "resistant": 3175, "outer": 3176, "logical": 3177, "rational": 3178, "leadership": 3179, "presence": 3180, "suggestion": 3181, "acquisitive": 3182, "commonality": 3183, "humour": 3184, "intangible": 3185, "117\u201318": 3186, "employer": 3187, "increasingly": 3188, "pp": 3189, "psychometric": 3190, "testing": 3191, "interviewee": 3192, "interviewer": 3193, "acceptable": 3194, "academic": 3195, "minimal": 3196, "convert": 3197, "trim": 3198, "attorney": 3199, "goldblum": 3200, "farmer": 3201, "french": 3202, "hub": 3203, "ransom": 3204, "192": 3205, "totally": 3206, "boost": 3207, "dramatic": 3208, "similarly": 3209, "agent": 3210, "hormonal": 3211, "common\u2014": 3212, "prove": 3213, "seve": 3214, "christie": 3215, "linford": 3216, "panasonic": 3217, "1992": 3218, "association": 3219, "britain": 3220, "gold": 3221, "gunnell": 3222, "medallist": 3223, "sally": 3224, "sporting": 3225, "track": 3226, "writers": 3227, "gascoigne": 3228, "overshadow": 3229, "treat": 3230, "atkinson": 3231, "entertain": 3232, "flash": 3233, "fortunately": 3234, "irresistible": 3235, "outrageous": 3236, "loathe": 3237, "forceful": 3238, "sugar": 3239, "venables": 3240, "ingredient": 3241, "abandon": 3242, "constance": 3243, "stifle": 3244, "affection": 3245, "anger": 3246, "childlike": 3247, "frustration": 3248, "orang": 3249, "empty": 3250, "kinda": 3251, "relive": 3252, "slide": 3253, "spooky": 3254, "tedium": 3255, "attest": 3256, "tape": 3257, "bury": 3258, "strain": 3259, "teenager": 3260, "abrupt": 3261, "mood": 3262, "prone": 3263, "bar": 3264, "contestant": 3265, "crew": 3266, "therapy": 3267, "closer": 3268, "broken": 3269, "heighten": 3270, "louris": 3271, "mark": 3272, "olson": 3273, "brilliant": 3274, "capriati": 3275, "glue": 3276, "gorgeous": 3277, "magnificent": 3278, "condescend": 3279, "deprivation": 3280, "hoarder": 3281, "peace": 3282, "pity": 3283, "poverty": 3284, "chorus": 3285, "fields": 3286, "jovial": 3287, "invade": 3288, "aplenty": 3289, "financial": 3290, "distortion": 3291, "conceal": 3292, "endlessly": 3293, "fatigue": 3294, "impatience": 3295, "reassuring": 3296, "behave": 3297, "oddly": 3298, "surprise": 3299, "worthwhile": 3300, "execute": 3301, "artistic": 3302, "erudition": 3303, "sensibility": 3304, "witness": 3305, "dispute": 3306, "chronicler": 3307, "favourable": 3308, "henry": 3309, "unpleasing": 3310, "massive": 3311, "monumental": 3312, "presto": 3313, "shock": 3314, "ultra": 3315, "violet": 3316, "christine": 3317, "hardaker": 3318, "homosexual": 3319, "integrity": 3320, "october": 3321, "storr": 3322, "extend": 3323, "reservation": 3324, "commonplace": 3325, "wordsworth": 3326, "defiance": 3327, "ordinary": 3328, "feminist": 3329, "fitful": 3330, "giles": 3331, "pat": 3332, "pearce": 3333, "radice": 3334, "ride": 3335, "tag": 3336, "thane": 3337, "disconcerting": 3338, "diverse": 3339, "wootton": 3340, "aura": 3341, "lyric": 3342, "melody": 3343, "snatch": 3344, "tender": 3345, "multidimensional": 3346, "affable": 3347, "glance": 3348, "scarcely": 3349, "ariosto": 3350, "hoole": 3351, "lend": 3352, "liken": 3353, "mercurial": 3354, "quicksilver": 3355, "erotic": 3356, "mahr": 3357, "guitarist": 3358, "nme": 3359, "bez": 3360, "interact": 3361, "monday": 3362, "shaun": 3363}